{
  "meta": {
    "quizId": "template",
    "version": "1.0",
    "createdAt": "2026-04-07",
    "updatedAt": "2026-04-07"
  },
  "prequiz": {
    "title": "Web Development Fundamentals",
    "subtitle": "Key concepts to review before the quiz",
    "description": "Familiarise yourself with these terms. A few Pokémon names are mixed in for fun — can you spot them?",
    "icon": "🌐"
  },
  "keywords": [
    {
      "term": "HTML",
      "definition": "HyperText Markup Language — the standard language used to structure content on the web using elements and tags.",
      "category": "Web Basics"
    },
    {
      "term": "CSS",
      "definition": "Cascading Style Sheets — a stylesheet language that controls the visual presentation of HTML elements.",
      "category": "Web Basics"
    },
    {
      "term": "JavaScript",
      "definition": "A high-level, interpreted programming language that enables dynamic behaviour and interactivity in web pages.",
      "category": "Web Basics"
    },
    {
      "term": "DOM",
      "definition": "Document Object Model — a programming interface that represents an HTML or XML document as a tree of nodes.",
      "category": "Browser"
    },
    {
      "term": "HTTP",
      "definition": "HyperText Transfer Protocol — the foundation of data communication on the web, used to transfer web resources.",
      "category": "Networking"
    },
    {
      "term": "REST API",
      "definition": "Representational State Transfer API — an architectural style for building web services using standard HTTP methods.",
      "category": "APIs"
    },
    {
      "term": "JSON",
      "definition": "JavaScript Object Notation — a lightweight, human-readable data-interchange format commonly used in web APIs.",
      "category": "Data"
    },
    {
      "term": "CSS Flexbox",
      "definition": "A CSS layout model that allows items in a container to align and distribute space flexibly along a single axis.",
      "category": "CSS"
    },
    {
      "term": "CSS Grid",
      "definition": "A two-dimensional CSS layout system that arranges elements into rows and columns.",
      "category": "CSS"
    },
    {
      "term": "Semantic HTML",
      "definition": "HTML tags that carry meaning about the content they contain, such as <header>, <article>, <nav>, and <footer>.",
      "category": "HTML"
    },
    {
      "term": "Responsive Design",
      "definition": "A web design approach that makes pages render well across a variety of devices and screen sizes.",
      "category": "Design"
    },
    {
      "term": "Accessibility (a11y)",
      "definition": "The practice of designing and building web content that can be used by people with a wide range of abilities and disabilities.",
      "category": "Design"
    },
    {
      "term": "Event Loop",
      "definition": "JavaScript's mechanism for handling asynchronous operations by queuing callbacks and executing them one at a time.",
      "category": "JavaScript"
    },
    {
      "term": "Promise",
      "definition": "A JavaScript object representing the eventual completion or failure of an asynchronous operation.",
      "category": "JavaScript"
    },
    {
      "term": "async / await",
      "definition": "Syntax that makes asynchronous, Promise-based code easier to read and write, behaving more like synchronous code.",
      "category": "JavaScript"
    }
  ]
}
